[{"senderKeyId":2064051284,"senderChainKey":{"iteration":163,"seed":"IMVL0E1lzO4FcB1oFXjqUokcopSFZ2Wbk9tvhtgmiaI="},"senderSigningKey":{"public":"BSilpItJd+qlIpOInE1KUYgdgOCYs6YPkCShzGfhNyUI","private":"QETr8lWNvMVSt7k7pfyRzWWri9CtVrNt34y4eSOU0VM="},"senderMessageKeys":[{},{},{},{},{},{},{},{},{},{},{},{},{},{},{},{},{},{},{},{},{},{},{},{},{},{},{},{},{},{},{},{},{},{},{},{},{},{},{},{},{},{},{},{},{},{},{},{},{},{},{},{},{},{},{},{},{},{},{},{},{},{},{},{},{},{},{},{},{},{},{},{},{},{},{},{},{},{},{},{},{}]}]