[{"senderKeyId":735663694,"senderChainKey":{"iteration":305,"seed":"BbSBzQjflwO4c2HXDpI4daZ+fq40OGEYf9GEuU3p2Go="},"senderSigningKey":{"public":"Bb/n9fdddi9zNWPjsQxlwi4M/TSo/VUjM0t1QlEdTzAJ","private":"AIlKRBHYzBT4XysjGgpURKuUMF/IksDdzMNn5byk+WE="},"senderMessageKeys":[{"iteration":1,"seed":"KR4kexgwcIJXAvFvBXNBroVdPbJOaU00219t4dIG108="},{},{},{},{},{},{},{},{},{},{},{},{},{},{},{},{},{},{},{},{},{},{},{},{},{},{},{},{},{},{},{},{},{},{},{},{},{},{},{},{},{},{},{},{},{},{},{},{},{},{},{},{},{},{},{},{},{},{},{},{},{},{},{},{},{},{},{},{},{},{},{},{},{},{},{},{},{},{},{},{},{},{},{},{},{},{},{},{},{},{},{},{},{},{},{},{},{},{},{},{},{},{},{},{},{},{},{},{},{},{},{},{},{},{},{},{},{},{},{},{},{},{},{},{},{},{},{},{},{},{},{},{},{},{},{},{},{},{},{},{},{},{},{},{},{},{},{},{},{},{},{}]}]